{"py/object": "rasa.core.featurizers.tracker_featurizers.MaxHistoryTrackerFeaturizer", "state_featurizer": {"py/object": "rasa.core.featurizers.single_state_featurizer.SingleStateFeaturizer", "_default_feature_states": {"intent": {"afirmacion": 0, "back": 1, "bot": 2, "despedida": 3, "fecha_fundacion_empresa": 4, "fundador_empresa": 5, "negacion": 6, "nlu_fallback": 7, "nuestras_instalaciones": 8, "nuestro_equipo": 9, "out_of_scope": 10, "politica_calidad": 11, "restart": 12, "saludo": 13, "session_start": 14, "sobre_nosotros": 15}, "action_name": {"action_listen": 0, "action_restart": 1, "action_session_start": 2, "action_default_fallback": 3, "action_deactivate_loop": 4, "action_revert_fallback_events": 5, "action_default_ask_affirmation": 6, "action_default_ask_rephrase": 7, "action_two_stage_fallback": 8, "action_unlikely_intent": 9, "action_back": 10, "...": 11, "action_extract_slots": 12, "action_politica_calidad": 13, "utter_afirmacion": 14, "utter_bot": 15, "utter_despedida": 16, "utter_negacion": 17, "utter_nuestras_instalaciones": 18, "utter_nuestro_equipo": 19, "utter_politica_calidad_certificado": 20, "utter_politica_calidad_general": 21, "utter_saludo": 22}, "entities": {"certificado": 0}, "slots": {}, "active_loop": {}}, "action_texts": [], "entity_tag_specs": []}, "max_history": 5, "remove_duplicates": true}